{
  "$schema": "https://raw.githubusercontent.com/googleapis/release-please/main/schemas/config.json",
  "packages": {
    ".": {
      "package-name": "dionysus",
      "release-type": "simple",
      "changelog-path": "CHANGELOG.md",
      "bump-minor-pre-major": true,
      "include-component-in-tag": false,
      "extra-files": [
        {
          "type": "toml",
          "path": "python/pyproject.toml",
          "jsonpath": "$.project.version"
        },
        {
          "type": "json",
          "path": "frontend/package.json",
          "jsonpath": "$.version"
        },
        {
          "type": "toml",
          "path": "python/uv.lock",
          "jsonpath": "$.package[?(@.name.value==\"dionysus\")].version"
        }
      ]
    }
  }
}
